Workbook

Sheet Parts & Costs
A1: Water Pressure Rocket — Avionics Bill of Materials
A2: Prices as shown in the shopping carts on 04 Aug 2026. Stores: Circuit Rocks (Manila) and Makerlab PH (Manila). Shipping and tax not included. Phase 1 = minimum viable flight computer; Phase 2 = full telemetry / research payload.
A4: Category | B4: Item | C4: Store | D4: SKU | E4: Qty | F4: Unit Price | G4: Line Total | H4: Phase | I4: What it does | J4: Why this part | K4: Alternatives / notes | L4: Product Link
A5: Compute | B5: Raspberry Pi Pico (with headers) | C5: Makerlab | D5: — | E5: 1 | F5: 459 | G5: =E5*F5 -> 459 | H5: 1 | I5: Flight computer. Runs the sensor loop, state machine and deployment logic. | J5: 264 KB RAM holds the entire 10 s flight in memory, so nothing is written to flash during the 50 g boost. Dual core lets the radio run isolated from the timing-critical sensor loop. | K5: RP2040-Zero (more GPIO, smaller); XIAO RP2040 (lightest). Rejected: ATmega328 Nano (2 KB RAM, cannot buffer a flight) and ESP32 (radio stack causes interrupt jitter). Plain Pico, not W — WiFi is dead weight in the nose and the CYW43 chip takes GP23/24/25/29. | L5: Open product page
A6: Compute | B6: Raspberry Pi Pico W (ground station) | C6: Makerlab | D6: MLE04027 | E6: 1 | F6: 590 | G6: =E6*F6 -> 590 | H6: 2 | I6: Ground station receiver. Takes the LoRa downlink and serves it to your phone over WiFi. | J6: On the ground, mass and pin pressure don't apply, so the WiFi earns its keep: run a soft AP, connect your phone, watch live altitude with no laptop in the field. LoRa sits on SPI0 (GP16–19) so there is no clash with the CYW43 pins. | K6: Heltec WiFi LoRa 32 / TTGO LoRa32 (~₱1,200–1,800) bundles ESP32 + SX1276 + OLED in one board and would replace this plus one RFM95W. NOTE: the with-headers variant (₱575) is sold out; ₱590 is the without-headers price. | L6: Open product page
A7: Sensor | B7: GY-63 MS5611-01BA03 barometer | C7: Circuit Rocks | D7: AB034 | E7: 1 | F7: 421 | G7: =E7*F7 -> 421 | H7: 1 | I7: Primary altimeter and apogee detector. Peak-and-drop logic fires the parachute. | J7: ~10 cm resolution at ~100 Hz. Its two error sources (dynamic pressure and inertial gradient) scale with velocity and acceleration, so both vanish at apogee — exactly where the reading matters. | K7: BMP390 (~5 cm, 200 Hz) is marginally better. BMP280 (~1 m) is flyable with a widened threshold. MPL3115A2 rejected: max ~1–10 Hz gives only 3–30 samples on a 3 s ascent. | L7: Open product page
A8: Sensor | B8: Pololu MinIMU-9 v6 (LSM6DSO + LIS3MDL) | C8: Circuit Rocks | D8: POL2862 | E8: 1 | F8: 2238 | G8: =E8*F8 -> 2238 | H8: 2 | I8: Coast-phase acceleration, gyro attitude, magnetometer heading. Tilt-based apogee backup and flight-path reconstruction. | J8: Gyros are the only source of orientation — no accelerometer can supply it. ±16 g gives fine resolution once boost forces are gone. Proper regulator, level shifting and decoupling, unlike clone boards. | K8: HW-123 / MPU-6050 at ~₱150 is adequate for a 10 s flight and saves ~₱2,100. ICM-42688-P (±4000 dps) is the real fix if the airframe spins past the ±2000 dps ceiling. | L8: Open product page
A9: Sensor | B9: Adafruit ADXL375 high-g accelerometer ±200 g | C9: Circuit Rocks | D9: 5374 | E9: 1 | F9: 2096 | G9: =E9*F9 -> 2096 | H9: 2 | I9: Boost-phase acceleration, launch detection, burnout timing. | J9: The only sensor that does not saturate during the 0.2–0.4 s burn at 20–100 g. Everything else clips at ±16 g and records a flat plateau. | K9: H3LIS331DL (±100/200/400 g) is cheaper with selectable range. Not required for flight 1 — the IMU still detects launch, it just clips. NOTE: ADXL345 is only ±16 g and cannot do this job. | L9: Open product page
A10: Sensor | B10: SparkFun GPS Breakout SAM-M8Q (u-blox) | C10: Circuit Rocks | D10: GPS-15210 | E10: 1 | F10: 2348 | G10: =E10*F10 -> 2348 | H10: 2 | I10: Landing coordinates. A recovery beacon, not a flight sensor — it will lose lock at launch and take 5–15 s to reacquire. | J10: Integrated antenna with u-blox's own RF design removes the commonest silent failure mode. Multi-GNSS including QZSS, which covers the Philippines well. Backup battery gives fast hot starts between flights. | K10: Adafruit Ultimate GPS (GPS-only, 34 s warm start, smaller board, no airborne dynamic model). ZOE-M8Q if the 40×40 mm footprint won't fit the nose cone. | L10: Open product page
A11: Radio | B11: Adafruit RFM95W LoRa Breakout 868/915 MHz | C11: Makerlab | D11: — | E11: 2 | F11: 1599 | G11: =E11*F11 -> 3198 | H11: 2 | I11: Live telemetry downlink plus post-landing position beacon. One unit flies, one is the ground station. | J11: LoRa spread spectrum buys ~10–20 dB of link budget over FSK — decisive when the rocket lands in wet grass with its antenna horizontal. SX1276 tunes 862–1020 MHz, so frequency is a firmware choice. | K11: RFM69HCW (FSK, ~500 m) if LoRa is out of stock — adequate at your ranges. RFM96W is 433 MHz and will NOT tune to 868 properly. See the Design Notes sheet before setting frequency. | L11: Open product page
A12: Recovery | B12: MG90D metal-gear micro servo, 180°, 1.8 kg | C12: Circuit Rocks | D12: AF016 | E12: 1 | F12: 192 | G12: =E12*F12 -> 192 | H12: 1 | I12: Pulls the latch pin that releases the nose cone / parachute bay. | J12: Positional (not continuous-rotation) so it moves to a commanded angle and holds. Metal gears survive the 50 g boost and hard landings where plastic gears strip. | K12: SG90 (plastic gears, cheaper, less shock-tolerant). Nichrome burn-wire as an independent backup channel. AVOID the 360° MG90D — it takes speed commands, not angles. | L12: Open product page
A13: Recovery | B13: LS3040 piezo buzzer (4 kHz, 2 mA) | C13: Makerlab | D13: — | E13: 1 | F13: 49 | G13: =E13*F13 -> 49 | H13: 1 | I13: Audible locator on landing; arming and status confirmation on the pad. | J13: 4 kHz sits near peak human hearing sensitivity. 2 mA draw means it can chirp for hours. The cheapest genuinely useful part on the board — it works when the radio doesn't. | K13: Active buzzer module (2.3 kHz, 25 mA, onboard transistor). This unit is active, so no frequency sweep — use chirp patterns instead, which gives most of the localisation benefit. | L13: Open product page
A14: Safety | B14: Reed switch 2×14 mm normally-open (10 pcs) | C14: Circuit Rocks | D14: AL040 | E14: 1 | F14: 149 | G14: =E14*F14 -> 149 | H14: 1 | I14: Arming switch. Separates 'powered on' from 'deployment live'. | J14: Sealed inside the airframe, actuated by a magnet from outside — no hole to admit water, nothing protruding to snap off. Prevents the servo firing while your hands are in the bay packing the chute. | K14: Nylon screw switch (latching, visible armed state). Hall effect sensor (no moving parts, immune to vibration) if reeds prove fragile. Pack of 10 because the glass envelope cracks easily. | L14: Open product page
A15: Safety | B15: Neodymium magnet N35 8×5 mm | C15: Circuit Rocks | D15: 2775 | E15: 1 | F15: 15 | G15: =E15*F15 -> 15 | H15: 1 | I15: Actuates the reed switch through the nose cone wall. | J15: Comfortably strong enough to close a 14 mm reed at a few centimetres through plastic. Tape it in place to arm; peel it off to disarm on recovery. | K15: Any N35+ neodymium of similar size. Keep it well away from the LIS3MDL magnetometer and the LiPo. | L15: Open product page
A16: Power | B16: PKCell 500 mAh LiPo 3.7 V (LP503035) | C16: Makerlab | D16: — | E16: 1 | F16: 200 | G16: =E16*F16 -> 200 | H16: 1 | I16: Powers the flight computer. Feeds Pico VSYS directly, no regulator needed. | J16: ~5 h runtime at ~100 mA draw, and only 10.5 g. Integrated protection circuitry (over-charge, over-discharge, short). Genuine JST-PH connector. | K16: Rejected: 2×18650 (~90 g, 30 h runtime, needs a buck converter) — 15× the energy at 12× the mass, and nose mass directly costs apogee. Hard-mount in foam; never let it float loose. | L16: Open product page
... A30: Build | B30: 40-pin jumper wires, 20 cm (third variant) | C30: Makerlab | D30: — | E30: 1 | F30: 59 | G30: =E30*F30 -> 59 | H30: 1 | I30: Third gender of jumper wire — likely female-female, confirm the variant at checkout. | J30: Completes the set so any module-to-module or module-to-breadboard connection is possible without improvising. | K30: Verify which gender this variant is before ordering; the product slug is shared across all three. | L30: Open product page
B32: GRAND TOTAL (both stores) | G32: =SUM(G5:G30) -> 13648
B33: Circuit Rocks subtotal | G33: =SUMIFS(G5:G30,C5:C30,"Circuit Rocks") -> 8766
B34: Makerlab subtotal | G34: =SUMIFS(G5:G30,C5:C30,"Makerlab") -> 4882
B36: Phase 1 subtotal — minimum viable flight computer | G36: =SUMIFS(G5:G30,H5:H30,1) -> 3153
B37: Phase 2 subtotal — GPS, IMU, high-g accel, LoRa pair | G37: =SUMIFS(G5:G30,H5:H30,2) -> 10495
B39: ASSUMPTION: the Makerlab cart displays a ₱25.00 / ₱35.00 unit price for the two protoboard sizes but a line total of ₱25.00 / ₱35.00 at qty 2. Unit price is entered here as ₱12.50 / ₱17.50 so the sheet reconciles with the ₱4,543.00 subtotal shown in the cart. Verify at checkout — this may be a cart display bug.
B40: Blue cells are hardcoded inputs (prices copied from the carts, 04 Aug 2026). Black cells are formulas.

Sheet Store Summary
A1: Cost by Store
A2: Calculated totals cross-checked against the subtotals displayed in each shopping cart.
A4: Store | B4: Location / terms | C4: Units | D4: Current Subtotal | E4: Original Cart (04 Aug) | F4: Added Since
A5: Circuit Rocks | B5: Manila — same-day ship before 4 PM; free shipping unlocked | C5: =SUMIFS('Parts & Costs'!E5:E30,'Parts & Costs'!C5:C30,A5) -> 15 | D5: =SUMIFS('Parts & Costs'!G5:G30,'Parts & Costs'!C5:C30,A5) -> 8766 | E5: 8255 | F5: =D5-E5 -> 511
A6: Makerlab | B6: Makerlab Manila — tax included, shipping at checkout | C6: =SUMIFS('Parts & Costs'!E5:E30,'Parts & Costs'!C5:C30,A6) -> 15 | D6: =SUMIFS('Parts & Costs'!G5:G30,'Parts & Costs'!C5:C30,A6) -> 4882 | E6: 4543 | F6: =D6-E6 -> 339
A7: TOTAL | C7: =SUM(C5:C6) -> 30 | D7: =SUM(D5:D6) -> 13648 | E7: =SUM(E5:E6) -> 12798 | F7: =SUM(F5:F6) -> 850
A9: 'Original Cart (04 Aug)' is the subtotal each cart displayed before this revision (Circuit Rocks ₱8,255.00; Makerlab ₱4,543.00). 'Added Since' is the net change from dropping the second plain Pico and adding the Pico W, JST-PH connectors, switched battery breakout, SPDT toggle, solder wire and the third jumper variant. Neither figure includes shipping.

Sheet Phasing
A1: Build Phasing — Risk vs Cost
A2: Water rocket recovery fails often on early flights. Flying a cheap configuration first proves the airframe, chute packing and deployment mechanism before expensive sensors are exposed to a hard landing.
A4: Phase | B4: Contents | C4: Cost | D4: % of Total | E4: Rationale
A5: Phase 1 | B5: Pico ×2, MS5611 barometer, servo, buzzer, reed switch + magnet, LiPo + charger, passives, protoboard, breadboards, jumper wires | C5: =SUMIFS('Parts & Costs'!G5:G30,'Parts & Costs'!H5:H30,1) -> 3153 | D5: =C5/$C$7 -> 0.23102286 | E5: Everything needed to log altitude and deploy a parachute reliably. Baro-primary apogee detection with a timer backup is competitive on a 3 s ascent. Fly this 3–4 times first.
A6: Phase 2 | B6: SAM-M8Q GPS, Pololu MinIMU-9 v6, ADXL375 high-g accelerometer, RFM95W LoRa ×2 | C6: =SUMIFS('Parts & Costs'!G5:G30,'Parts & Costs'!H5:H30,2) -> 10495 | D6: =C6/$C$7 -> 0.76897714 | E6: Research payload: boost-phase g data, attitude reconstruction, live telemetry, GPS recovery. Add these to a vehicle whose recovery you already trust.
A7: TOTAL | C7: =SUM(C5:C6) -> 13648 | D7: =SUM(D5:D6) -> 1

Sheet Still Needed
A1: Not Yet in Either Cart
A2: Estimated Philippine street prices entered as blue placeholders — replace with real quotes. Some of these are tools you may already own.
A4: Item | B4: Category | C4: Est. Cost | D4: Why it's needed
A5: Multimeter | B5: Tool | C5: 500 | D5: The single most important tool. Continuity checking alone saves hours; verify LiPo polarity before connecting anything.
A6: Soldering iron, temperature-controlled | B6: Tool | C6: 1200 | D6: Every breakout ships with headers loose in the bag. Soldering is not optional. Set to ~330 C for the 63/37 solder already in the cart.
A7: Flux pen or paste | B7: Tool | C7: 200 | D7: Rosin-core solder has flux inside, but extra flux on the pad is what makes header joints suddenly feel easy. Essential for any rework.
A8: Solder wick, brass tip cleaner, helping hands | B8: Tool | C8: 400 | D8: Rework and cleanup. You will make bad joints while learning.
A9: USB logic analyzer, 8-channel clone (Sigrok/PulseView) | B9: Tool | C9: 450 | D9: Highest-value cheap debug tool for I2C. When the bus goes silent you will see exactly why.
A10: Data-capable USB cable for the Pico | B10: Tool | C10: 150 | D10: Half the cables in any drawer are charge-only. This wastes a surprising amount of time.
A11: 100 nF ceramic capacitors (assortment) | B11: Passive | C11: 100 | D11: Decoupling at every IC, alongside the 220 uF bulk caps already in the cart.
A12: M3 nylon standoffs 15-20 mm + screws | B12: Mechanical | C12: 150 | D12: Join the two avionics decks. Nylon not metal — lighter, and no accidental shorts.
A13: EVA foam sheet / soft silicone potting | B13: Mechanical | C13: 200 | D13: Shock isolation. A rigidly bolted PCB transmits the full 50 g spike; foam does not.
A14: Piano wire 1 mm + servo horn hardware | B14: Mechanical | C14: 150 | D14: The latch pin itself. Test the pull with the chute actually packed — friction is far higher than a bare bench test.
A15: Solid-core hookup wire 22 AWG | B15: Build | C15: 200 | D15: Clean short runs on the flight board. Jumper wires everywhere makes debugging miserable.
A16: Antenna wire for 82 mm quarter-wave | B16: Radio | C16: 50 | D16: 82 mm at 868 MHz (78 mm at 915). Cut accurately — wrong antenna length costs more range than any power setting.
... A20: Gore-Tex or hydrophobic mesh scrap | B20: Mechanical | C20: 100 | D20: Covers the static ports. A water droplet across a port gives wildly wrong pressure readings.
A21: ESTIMATED ADDITIONAL SPEND | C21: =SUM(C5:C20) -> 4650
A23: ASSUMPTION: every cost on this sheet is a rough estimate supplied as a placeholder, not a quote. They are shown in blue as hardcoded inputs — overwrite them with real prices.

Sheet Design Notes
A1: Key Design Decisions & Regulatory Notes
A2: The reasoning behind the parts chosen, and the constraints that drove them.
A4: Topic | B4: Decision | C4: Reasoning
A5: Apogee detection | B5: Barometer peak-and-drop is primary. Timer is backup. IMU tilt is an inhibit only. | C5: Baro differentiates a measured position — error is bounded and never accumulates. An IMU integrates acceleration — error is unbounded, grows from a clipped boost, and is undetectable without an external reference. Baro error sources (dynamic pressure ~ v², inertial gradient ~ a) both vanish at apogee.
A6: Detection latency | B6: MS5611 at ~10 cm noise needs ~30 cm of drop ≈ 0.25 s past apogee. A BMP280 at ~1 m would need ~0.7 s. | C6: Altitude near apogee follows h = h_max − ½gt², so the curve is flat there and sensor noise translates directly into detection delay. This is the entire argument for the MS5611 over the cheaper BMP280.
A7: Deployment lockout | B7: Inhibit deployment until boost has ended plus ~0.5 s. Latch the fire flag so it cannot retrigger. | C7: Prevents a boost-phase pressure transient firing the chute at 70 m/s. Bias every threshold toward late — late deployment costs some data, early deployment shreds the parachute.
A8: Static ports | B8: 3–4 holes of ~1 mm, evenly spaced, at least one body-diameter aft of the nose shoulder. | C8: Uneven or badly placed ports cause pressure asymmetry that reads as phantom altitude. Port quality dominates sensor noise if you get it wrong. Size for lag too — keep the bay time constant under ~50 ms.
A9: I2C bus | B9: MS5611 (0x77), LSM6DSO (0x6A), LIS3MDL (0x1C/0x1E), ADXL375 (0x53), GPS (0x42) — all on two wires. | C9: No address conflicts. Run at 400 kHz with short traces. Watch for clone boards carrying 2.2 kΩ pull-ups; three in parallel is too strong and the bus will misbehave.
A10: Firmware architecture | B10: Core 0: 500 Hz sensor loop and state machine, buffered in RAM. Core 1: LoRa TX, GPS parsing, flash dump after landing. | C10: No flash writes during the 50 g boost — the commonest way to lose a flight's data. If the radio stalls, core 1 stalls and core 0 never notices. Deployment logic must never depend on the link.
A11: Filtering | B11: Log raw counts in flight. Do Kalman fusion offline in Python. | C11: Iterate in seconds instead of reflashing and relaunching. Port the filter onboard only once it agrees with raw data across a dozen flights.
A12: LoRa frequency — CHECK THIS | B12: Configure to 868–870 MHz at +14 dBm, NOT the US 915 default. Verify current NTC rules yourself before flying. | C12: NTC MC 03-06-2017 lists PH non-specific SRD / telemetry bands as 868.000–868.600, 868.700–869.200 and 869.300–869.700 (25 mW erp), plus 869.700–870.000 (5 mW erp). Whether 915–918 (AS923-3) is permitted is actively disputed in the LoRa community. NTC MC 004-06-2026 amended SRD parameters again in June 2026 — check for anything newer.
A13: LoRa duty cycle | B13: EU-style bands typically carry a 1% duty cycle limit. | C13: At SF7/BW250 a 16-byte packet is ~10 ms airtime, so 20 Hz telemetry is ~20% duty. Either slow the live stream toward ~1 Hz, or accept the tradeoff knowingly. A landed beacon at one packet per 5 s is comfortably within limits.
A14: Mass budget | B14: ~80 g total avionics, all of it in the nose cone. | C14: A water rocket has fixed impulse from its pressure vessel, so every gram of dry mass directly costs apogee. Nose mass also shifts CG forward, requiring larger fins to keep CP aft of it.
A15: Arming sequence | B15: Battery in → pack chute → seat cone → mount on launcher → ARM with magnet → step back → pressurise. | C15: Arming is the last action, performed from outside a sealed airframe. Disarming is the first action on recovery, before touching the rocket. A buzzer chirp and a state field in the LoRa packet confirm it from 10 m away.
